epic/sklearn/__init__.py
epic/sklearn/composite.py
epic/sklearn/decomposition.py
epic/sklearn/ensemble.py
epic/sklearn/feature_selection/__init__.py
epic/sklearn/feature_selection/mutual_info.py
epic/sklearn/general.py
epic/sklearn/metrics/__init__.py
epic/sklearn/metrics/leven/.gitignore
epic/sklearn/metrics/leven/CMakeLists.txt
epic/sklearn/metrics/leven/indices.h
epic/sklearn/metrics/leven/leven.cpp
epic/sklearn/metrics/leven/levenshtein.h
epic/sklearn/metrics/leven/levenshtein_impl.h
epic/sklearn/metrics/leven/parallel.h
epic/sklearn/metrics/leven/pystring.h
epic/sklearn/metrics/leven.cpython-310-x86_64-linux-gnu.so
epic/sklearn/metrics/ranking.py
epic/sklearn/metrics/reports.py
epic/sklearn/metrics/scores.py
epic/sklearn/neighbors/__init__.py
epic/sklearn/neighbors/base.py
epic/sklearn/neighbors/unsupervised.py
epic/sklearn/neighbors/weight.py
epic/sklearn/pipeline.py
epic/sklearn/plot.py
epic/sklearn/preprocessing/__init__.py
epic/sklearn/preprocessing/categorical.py
epic/sklearn/preprocessing/data.py
epic/sklearn/preprocessing/general.py
epic/sklearn/preprocessing/label.py
epic/sklearn/typing.py
epic/sklearn/utils/__init__.py
epic/sklearn/utils/data.py
epic/sklearn/utils/general.py
epic/sklearn/utils/kneedle.py
epic/sklearn/utils/thresholding.py
epic/sklearn/utils/validation.py
epic_sklearn-1.1.2.dist-info/LICENSE.md
epic_sklearn-1.1.2.dist-info/METADATA
epic_sklearn-1.1.2.dist-info/WHEEL
epic_sklearn-1.1.2.dist-info/RECORD
