Metadata-Version: 2.3
Name: epic-sklearn
Version: 1.1.2
Summary: An expansion pack for scikit-learn
License: MIT
Author: Assaf Ben-David
Requires-Python: >=3.10,<4.0
Classifier: License :: OSI Approved :: MIT License
Classifier: Programming Language :: Python :: 3
Classifier: Programming Language :: Python :: 3.10
Classifier: Programming Language :: Python :: 3.11
Classifier: Programming Language :: Python :: 3.12
Classifier: Programming Language :: Python :: 3.13
Requires-Dist: cytoolz
Requires-Dist: epic-common
Requires-Dist: epic-logging
Requires-Dist: epic-pandas
Requires-Dist: joblib
Requires-Dist: matplotlib
Requires-Dist: numpy (>=1.21.5)
Requires-Dist: pandas (>=1.4.4)
Requires-Dist: scikit-learn (>=1.2.2,<2.0.0)
Requires-Dist: scipy (>=1.7.3)
Requires-Dist: ultima
Project-URL: Repository, https://github.com/epic-framework/epic-sklearn
